freshservice/__init__.py
freshservice/api.py
freshservice/errors.py
freshservice/models.py
freshservice_wrapper-1.5.dist-info/METADATA
freshservice_wrapper-1.5.dist-info/RECORD
freshservice_wrapper-1.5.dist-info/WHEEL
freshservice_wrapper-1.5.dist-info/top_level.txt
