Metadata-Version: 2.1
Name: freshservice-wrapper
Version: 1.5
Summary: An API wrapper for Freshservice
Home-page: https://bitbucket.org/egym-com/freshservice-wrapper/
Author: Lennart Weiss
Author-email: lennart.weiss@egym.de
License: UNKNOWN
Platform: UNKNOWN
Classifier: Programming Language :: Python :: 3
Classifier: License :: OSI Approved :: Apache Software License
Classifier: Operating System :: OS Independent
Requires-Python: >=3
Requires-Dist: requests
